pixtreme_upscale/__init__.py
pixtreme_upscale/onnx_upscaler.py
pixtreme_upscale/torch_upscaler.py
pixtreme_upscale/trt_upscaler.py
pixtreme_upscale/utils/__init__.py
pixtreme_upscale/utils/layout.py
pixtreme_upscale/utils/model_convert.py
pixtreme_upscale-0.8.6.dist-info/METADATA
pixtreme_upscale-0.8.6.dist-info/WHEEL
pixtreme_upscale-0.8.6.dist-info/licenses/LICENSE
pixtreme_upscale-0.8.6.dist-info/RECORD
