Metadata-Version: 2.4
Name: pixtreme-upscale
Version: 0.8.6
Summary: Multi-backend deep learning upscalers for pixtreme
Project-URL: repository, https://github.com/sync-dev-org/pixtreme
Project-URL: issues, https://github.com/sync-dev-org/pixtreme/issues
Author-email: minamik <mia@sync.dev>
License-Expression: MIT
License-File: LICENSE
Classifier: Development Status :: 4 - Beta
Classifier: Environment :: GPU :: NVIDIA CUDA :: 12
Classifier: Intended Audience :: Developers
Classifier: License :: OSI Approved :: MIT License
Classifier: Operating System :: Microsoft :: Windows
Classifier: Operating System :: POSIX :: Linux
Classifier: Programming Language :: Python :: 3.12
Classifier: Programming Language :: Python :: 3.13
Classifier: Topic :: Multimedia :: Graphics
Classifier: Topic :: Scientific/Engineering :: Artificial Intelligence
Classifier: Topic :: Software Development :: Libraries
Requires-Python: >=3.12
Requires-Dist: basicsr-fixed>=1.4.2
Requires-Dist: onnx-graphsurgeon
Requires-Dist: onnx>=1.18.0
Requires-Dist: onnxconverter-common>=1.13.0
Requires-Dist: onnxruntime-gpu>=1.22.0
Requires-Dist: pixtreme-core>=0.8.6
Requires-Dist: spandrel-extra-arches>=0.2.0
Requires-Dist: spandrel>=0.4.1
Requires-Dist: torch>=2.0
Provides-Extra: tensorrt
Requires-Dist: tensorrt-cu12>=10.11.0.33; extra == 'tensorrt'
